cv2watermark/LICENSE
cv2watermark/README.MD
cv2watermark/__init__.py
cv2watermark/requirements.txt
cv2watermark/thirdparty.json
cv2watermark-0.10.dist-info/LICENSE.rst
cv2watermark-0.10.dist-info/METADATA
cv2watermark-0.10.dist-info/WHEEL
cv2watermark-0.10.dist-info/top_level.txt
cv2watermark-0.10.dist-info/RECORD
